ipyupload/__init__.py
ipyupload/__meta__.py
ipyupload/ipyupload.json
ipyupload/params.py
ipyupload/util.py
ipyupload/widget_upload.py
ipyupload/widget_upload_box.py
ipyupload/static/extension.js
ipyupload/static/index.js
ipyupload/static/index.js.map
ipyupload-0.1.3.data/data/etc/jupyter/nbconfig/notebook.d/ipyupload.json
ipyupload-0.1.3.data/data/share/jupyter/nbextensions/ipyupload/extension.js
ipyupload-0.1.3.data/data/share/jupyter/nbextensions/ipyupload/index.js
ipyupload-0.1.3.data/data/share/jupyter/nbextensions/ipyupload/index.js.map
ipyupload-0.1.3.dist-info/DESCRIPTION.rst
ipyupload-0.1.3.dist-info/METADATA
ipyupload-0.1.3.dist-info/RECORD
ipyupload-0.1.3.dist-info/WHEEL
ipyupload-0.1.3.dist-info/metadata.json
ipyupload-0.1.3.dist-info/top_level.txt
