Metadata-Version: 2.0
Name: ipyupload
Version: 0.1.3
Summary: Jupyter widget - upload file from browser
Home-page: https://gitlab.com/oscar6echo/ipyupload
Author: oscar6echo
Author-email: oscar6echo@gmail.com
License: MIT
Download-URL: https://gitlab.com/oscar6echo/ipyupload-dev/repository/archive.tar.gz?ref=0.1.3
Keywords: ipyupload,javascript,filereader,browser API
Platform: UNKNOWN
Classifier: Development Status :: 4 - Beta
Classifier: License :: OSI Approved :: MIT License
Classifier: Programming Language :: Python :: 3.6
Classifier: Programming Language :: Python :: 3.7
Requires-Dist: ipywidgets (>=7.4.2)
